colorunittest/__init__.py
colorunittest/color_unittest.py
colorunittest-0.0.2.dist-info/LICENSE
colorunittest-0.0.2.dist-info/METADATA
colorunittest-0.0.2.dist-info/WHEEL
colorunittest-0.0.2.dist-info/top_level.txt
colorunittest-0.0.2.dist-info/RECORD
