Metadata-Version: 2.1
Name: colorunittest
Version: 0.0.2
Summary: Reformatting and coloring unittest output in Jupyter Notebooks
Home-page: https://github.com/hilariesit/colorunittest
Author: Hilarie Sit
Author-email: hs764@cornell.edu
License: UNKNOWN
Project-URL: Bug Tracker, https://github.com/hilariesit/colorunittest/issues
Platform: UNKNOWN
Classifier: Programming Language :: Python :: 3
Classifier: License :: OSI Approved :: MIT License
Classifier: Operating System :: OS Independent
Requires-Python: >=3.6
License-File: LICENSE
Requires-Dist: termcolor
